xia_sso_flask/__init__.py
xia_sso_flask/sso.cpython-311-darwin.so
xia_sso_flask-0.1.24.dist-info/LICENSE.txt
xia_sso_flask-0.1.24.dist-info/METADATA
xia_sso_flask-0.1.24.dist-info/WHEEL
xia_sso_flask-0.1.24.dist-info/top_level.txt
xia_sso_flask-0.1.24.dist-info/RECORD
