Metadata-Version: 2.1
Name: xia-sso-flask
Version: 0.1.24
Summary: UNKNOWN
Home-page: https://develop.x-i-a.com/docs/xia-sso-flask/0.1.24/index.html
Author: X-I-A
Author-email: admin@x-i-a.com
License: UNKNOWN
Platform: UNKNOWN
Requires-Python: >=3.9
License-File: LICENSE.txt
Requires-Dist: flask
Requires-Dist: xia-token-flask
Requires-Dist: xia-engine-rest
Requires-Dist: xia-user
